module/dma_arbiter.v
// =============================================================================
// Module  : dma_arbiter
// Project : DMA Controller 4-Channel
// Brief   : Bus Arbiter Round Robin thuần túy (không Fixed Priority).
//           Sau khi kênh i được grant, lần tiếp theo bắt đầu tìm từ i+1.
//           Đảm bảo fairness — mọi kênh đều được phục vụ, không starvation.
//
// Ports
//   clk         – clock hệ thống
//   rst_n       – reset đồng bộ tích cực thấp
//   req[3:0]    – yêu cầu từ 4 kênh (1 = kênh đang yêu cầu bus)
//   grant[3:0]  – cấp quyền cho kênh thắng (one-hot)
//   grant_valid – có ít nhất một grant đang active
// =============================================================================

`timescale 1ns / 1ps

module dma_arbiter (
    input  wire       clk,
    input  wire       rst_n,
    input  wire [3:0] req,        // Yêu cầu từ 4 kênh
    output reg  [3:0] grant,      // Grant (one-hot)
    output wire       grant_valid // Có kênh nào được grant không
);

    // ── Con trỏ Round Robin ──────────────────────────────────────────────────
    // next_ptr: kênh tiếp theo được xét ưu tiên trong vòng hiện tại
    reg [1:0] next_ptr;

    // ── Round Robin combinational logic ──────────────────────────────────────
    // Xoay vòng bắt đầu từ next_ptr, cấp grant cho kênh đầu tiên có req
    reg [3:0] next_grant;
    integer   i;
    integer   idx;
    always @(*) begin
        next_grant = 4'b0000;
        for (i = 0; i < 4; i = i + 1) begin
            idx = (next_ptr + i) & 2'h3;   // (next_ptr + i) mod 4
            if (req[idx] && next_grant == 4'b0000)
                next_grant[idx] = 1'b1;
        end
    end

    // ── Register grant + cập nhật con trỏ ───────────────────────────────────
    always @(posedge clk) begin
        if (!rst_n) begin
            grant    <= 4'b0000;
            next_ptr <= 2'd0;
        end else begin
            grant <= next_grant;

            // Cập nhật next_ptr: kênh vừa được grant + 1 (mod 4)
            if (next_grant != 4'b0000) begin
                case (next_grant)
                    4'b0001: next_ptr <= 2'd1;
                    4'b0010: next_ptr <= 2'd2;
                    4'b0100: next_ptr <= 2'd3;
                    4'b1000: next_ptr <= 2'd0;
                    default: next_ptr <= next_ptr;
                endcase
            end
        end
    end

    assign grant_valid = |grant;

endmodule

testbech/tb_dma_arbiter.v
// =============================================================================
// Testbench : tb_dma_arbiter
// Module    : dma_arbiter (Round Robin)
// Test cases:
//   TC1 – Chỉ 1 kênh yêu cầu → grant ngay cho kênh đó
//   TC2 – 2 kênh yêu cầu đồng thời → xoay vòng đúng thứ tự
//   TC3 – 4 kênh yêu cầu đồng thời → Round Robin quét đủ 4 kênh
//   TC4 – Con trỏ tiếp tục đúng sau khi kênh giải phóng
//   TC5 – Không kênh nào yêu cầu → grant = 0
//   TC6 – Kiểm tra không starvation: kênh sau cùng vẫn được phục vụ
// =============================================================================

// =============================================================================
// Testbench : tb_dma_arbiter
// Module    : dma_arbiter (Round Robin)
// Test cases:
//   TC1 - Chỉ 1 kênh yêu cầu → grant ngay cho kênh đó
//   TC2 - 2 kênh yêu cầu đồng thời → xoay vòng đúng thứ tự
//   TC3 - 4 kênh yêu cầu đồng thời → Round Robin quét đủ 4 kênh
//   TC4 - Con trỏ tiếp tục đúng sau khi kênh giải phóng
//   TC5 - Không kênh nào yêu cầu → grant = 0
//   TC6 - Kiểm tra không starvation: kênh sau cùng vẫn được phục vụ
// =============================================================================

`timescale 1ns / 1ps

module tb_dma_arbiter;

// ── DUT signals ──────────────────────────────────────────────────────────
    reg        clk, rst_n;
    reg  [3:0] req;
    wire [3:0] grant;
    wire       grant_valid;

// ── DUT ──────────────────────────────────────────────────────────────────
    dma_arbiter DUT (
        .clk(clk), .rst_n(rst_n),
        .req(req),
        .grant(grant),
        .grant_valid(grant_valid)
    );

// ── Clock 10 ns ──────────────────────────────────────────────────────────
    initial clk = 0;
    always #5 clk = ~clk;

    task reset_dut;
        begin
            rst_n = 0; req = 4'b0000;
            repeat(3) @(posedge clk); #1;
            rst_n = 1;
            @(posedge clk); #1;
        end
    endtask

    task tick(input integer n);
        begin
            repeat(n) @(posedge clk); #1;
        end
    endtask

    integer errors;

    initial begin
        $dumpfile("tb_dma_arbiter.vcd");
        $dumpvars(0, tb_dma_arbiter);
        errors = 0;

        // ══════════════════════════════════════════════════════════════════════
        // TC1: Chỉ 1 kênh yêu cầu
        // ══════════════════════════════════════════════════════════════════════
        $display("\n[TC1] Chi 1 kenh yeu cau");
        reset_dut;

        req = 4'b0001; tick(2);   // Chỉ CH0
        if (grant !== 4'b0001) begin
            $display("  FAIL: CH0 req -> grant expected 0001, got %b", grant);
            errors = errors + 1;
        end else $display("  PASS: CH0 -> grant = 0001");

        req = 4'b0000; tick(2);
        req = 4'b0100; tick(2);   // Chỉ CH2
        if (grant !== 4'b0100) begin
            $display("  FAIL: CH2 req -> grant expected 0100, got %b", grant);
            errors = errors + 1;
        end else $display("  PASS: CH2 -> grant = 0100");

        req = 4'b0000; tick(2);

        // ══════════════════════════════════════════════════════════════════════
        // TC2: 2 kênh yêu cầu đồng thời → xoay vòng
        // ══════════════════════════════════════════════════════════════════════
        $display("\n[TC2] 2 kenh yeu cau dong thoi: CH0 va CH2");
        reset_dut;

        req = 4'b0101;  // CH0 + CH2
        tick(1);
        $display("  Grant lan 1: %b", grant);

        begin : TC2_block // <--- SỬA LỖI: Đặt tên block cho TC2
            reg [3:0] first_grant;
            first_grant = grant;

            if (first_grant !== 4'b0001 && first_grant !== 4'b0100) begin
                $display("  FAIL: grant khong hop le: %b", first_grant);
                errors = errors + 1;
            end

            tick(1);
            // 1 chu ky → grant tiếp theo
            $display("  Grant lan 2: %b", grant);
            if (first_grant == 4'b0001 && grant !== 4'b0100) begin
                $display("  FAIL: sau CH0 phai la CH2, got %b", grant);
                errors = errors + 1;
            end else if (first_grant == 4'b0100 && grant !== 4'b0001) begin
                $display("  FAIL: sau CH2 phai la CH0, got %b", grant);
                errors = errors + 1;
            end else
                $display("  PASS: xoay vong dung: %b -> %b", first_grant, grant);
        end

        req = 4'b0000; tick(2);

        // ══════════════════════════════════════════════════════════════════════
        // TC3: 4 kênh yêu cầu đồng thời → Round Robin đủ 4 vòng
        // ══════════════════════════════════════════════════════════════════════
        $display("\n[TC3] 4 kenh yeu cau dong thoi -> Round Robin 4 vong");
        reset_dut;

        req = 4'b1111;  // Tất cả 4 kênh

        begin : TC3_block // <--- SỬA LỖI: Đặt tên block cho TC3
            reg [3:0] seen;
            reg [3:0] g;
            integer round;
            seen = 4'b0000;

            for (round = 0; round < 4; round = round + 1) begin
                tick(1);
                // 1 chu ky mỗi vòng
                g = grant;
                $display("  Vong %0d: grant = %b", round+1, g);
                if (g == 4'b0000) begin
                    $display("  FAIL: grant = 0 khi co request");
                    errors = errors + 1;
                end
                if (g != 4'b0001 && g != 4'b0010 && g != 4'b0100 && g != 4'b1000) begin
                    $display("  FAIL: grant khong phai one-hot: %b", g);
                    errors = errors + 1;
                end
                if (seen & g) begin
                    $display("  FAIL: kenh %b duoc grant 2 lan trong 4 vong", g);
                    errors = errors + 1;
                end
                seen = seen | g;
            end

            if (seen === 4'b1111)
                $display("  PASS: ca 4 kenh duoc phuc vu dung 1 lan");
            else begin
                $display("  FAIL: co kenh khong duoc phuc vu, seen = %b", seen);
                errors = errors + 1;
            end
        end

        req = 4'b0000;
        tick(2);

        // ══════════════════════════════════════════════════════════════════════
        // TC4: Con trỏ tiếp tục đúng sau khi kênh giải phóng
        // ══════════════════════════════════════════════════════════════════════
        $display("\n[TC4] Con tro tiep tuc sau khi kenh giai phong");
        reset_dut;

        // CH1 được grant, sau đó CH1 giải phóng, CH3 yêu cầu
        // Con trỏ phải ở CH2 sau khi CH1 xong → CH3 được phục vụ tiếp
        req = 4'b0010;
        tick(2);  // CH1
        if (grant !== 4'b0010) begin
            $display("  FAIL: CH1 expected");
            errors = errors + 1;
        end else $display("  CH1 grant OK");

        req = 4'b1000; tick(2);
        // CH1 xong, CH3 yêu cầu
        if (grant !== 4'b1000) begin
            $display("  FAIL: CH3 expected sau CH1 (next_ptr=2, quet den CH3)");
            errors = errors + 1;
        end else $display("  PASS: CH3 duoc grant dung sau CH1");

        req = 4'b0000; tick(2);

        // ══════════════════════════════════════════════════════════════════════
        // TC5: Không có kênh nào yêu cầu
        // ══════════════════════════════════════════════════════════════════════
        $display("\n[TC5] Khong co kenh yeu cau -> grant phai = 0");
        reset_dut;

        req = 4'b0000; tick(4);
        if (grant !== 4'b0000) begin
            $display("  FAIL: grant expected 0000, got %b", grant);
            errors = errors + 1;
        end else $display("  PASS: grant = 0000 khi khong co request");

        if (grant_valid !== 1'b0) begin
            $display("  FAIL: grant_valid expected 0");
            errors = errors + 1;
        end else $display("  PASS: grant_valid = 0");

        // ══════════════════════════════════════════════════════════════════════
        // TC6: Không starvation - CH3 luôn được phục vụ dù CH0 liên tục yêu cầu
        // ══════════════════════════════════════════════════════════════════════
        $display("\n[TC6] No starvation: CH0+CH3 yeu cau, CH3 phai duoc phuc vu");
        reset_dut;

        begin : TC6_block // <--- SỬA LỖI: Đặt tên block cho TC6
            integer ch3_served;
            integer cycle;
            ch3_served = 0;
            req = 4'b1001;  // CH0 + CH3 đồng thời
            for (cycle = 0; cycle < 8; cycle = cycle + 1) begin
                tick(2);
                if (grant === 4'b1000) ch3_served = ch3_served + 1;
            end

            $display("  CH3 duoc phuc vu %0d/4 vong", ch3_served);
            if (ch3_served == 0) begin
                $display("  FAIL: CH3 bi starvation (khong bao gio duoc grant)");
                errors = errors + 1;
            end else
                $display("  PASS: CH3 duoc phuc vu, khong co starvation");
        end

        // ── Kết quả ──────────────────────────────────────────────────────────
        $display("\n========================================");
        if (errors == 0)
            $display("  KET QUA: TAT CA TEST PASS [dma_arbiter]");
        else
            $display("  KET QUA: %0d TEST FAIL [dma_arbiter]", errors);
        $display("========================================\n");

        $finish;
    end

    initial begin #50000; $display("TIMEOUT"); $finish; end

endmodule

DMAc/DMAc.sim/sim_1/behav/xsim/tb_dma_arbiter.vcd
$date
   Sat May 16 14:42:40 2026
$end

$version
  2025.2
  $dumpfile ("tb_dma_arbiter.vcd") 
$end

$timescale
  1ps
$end

$scope module tb_dma_arbiter $end
$var reg 1 ! clk $end
$var reg 1 " rst_n $end
$var reg 4 # req [3:0] $end
$var wire 4 $ grant [3:0] $end
$var wire 1 % grant_valid $end
$var integer 32 & errors [31:0] $end
$scope module DUT $end
$var wire 1 ' clk $end
$var wire 1 ( rst_n $end
$var wire 4 ) req [3:0] $end
$var reg 4 * grant [3:0] $end
$var wire 1 % grant_valid $end
$var reg 2 + next_ptr [1:0] $end
$var reg 4 , next_grant [3:0] $end
$var integer 32 - i [31:0] $end
$var integer 32 . idx [31:0] $end
$upscope $end
$scope begin TC2_block $end
$var reg 4 / first_grant [3:0] $end
$upscope $end
$scope begin TC3_block $end
$var reg 4 0 seen [3:0] $end
$var reg 4 1 g [3:0] $end
$var integer 32 2 round [31:0] $end
$upscope $end
$scope begin TC6_block $end
$var integer 32 3 ch3_served [31:0] $end
$var integer 32 4 cycle [31:0] $end
$upscope $end
$scope task reset_dut $end
$upscope $end
$scope task tick $end
$var integer 32 5 n [31:0] $end
$upscope $end
$upscope $end
$enddefinitions $end

#0
$dumpvars
0!
0"
b0 #
bx $
x%
b0 &
0'
0(
b0 )
bx *
bx +
b0 ,
b100 -
b0xx .
bx /
bx 0
bx 1
bx 2
bx 3
bx 4
bx 5
$end

#5000
1!
b0 $
0%
1'
b0 *
b0 +
b100 -
b11 .

#10000
0!
0'

#15000
1!
1'

#20000
0!
0'

#25000
1!
1'

#26000
1"
1(

#30000
0!
0'

#35000
1!
1'

#36000
b1 #
b1 )
b1 ,
b100 -
b11 .
b10 5

#40000
0!
0'

#45000
1!
b1 $
1%
1'
b1 *
b1 +
b1 ,
b100 -
b0 .

#50000
0!
0'

#55000
1!
1'

#56000
b0 #
b0 )
b0 ,
b100 -
b0 .

#60000
0!
0'

#65000
1!
b0 $
0%
1'
b0 *

#70000
0!
0'

#75000
1!
1'

#76000
b100 #
b100 )
b100 ,
b100 -
b0 .

#80000
0!
0'

#85000
1!
b100 $
1%
1'
b100 *
b11 +
b100 ,
b100 -
b10 .

#90000
0!
0'

#95000
1!
1'

#96000
b0 #
b0 )
b0 ,
b100 -
b10 .

#100000
0!
0'

#105000
1!
b0 $
0%
1'
b0 *

#110000
0!
0'

#115000
1!
1'

#116000
0"
0(

#120000
0!
0'

#125000
1!
1'
b0 +
b100 -
b11 .

#130000
0!
0'

#135000
1!
1'

#140000
0!
0'

#145000
1!
1'

#146000
1"
1(

#150000
0!
0'

#155000
1!
1'

#156000
b101 #
b101 )
b1 ,
b100 -
b11 .
b1 5

#160000
0!
0'

#165000
1!
b1 $
1%
1'
b1 *
b1 +
b100 ,
b100 -
b0 .

#166000
b1 /

#170000
0!
0'

#175000
1!
b100 $
1'
b100 *
b11 +
b1 ,
b100 -
b10 .

#176000
b0 #
b0 )
b0 ,
b100 -
b10 .
b10 5

#180000
0!
0'

#185000
1!
b0 $
0%
1'
b0 *

#190000
0!
0'

#195000
1!
1'

#196000
0"
0(

#200000
0!
0'

#205000
1!
1'
b0 +
b100 -
b11 .

#210000
0!
0'

#215000
1!
1'

#220000
0!
0'

#225000
1!
1'

#226000
1"
1(

#230000
0!
0'

#235000
1!
1'

#236000
b1111 #
b1111 )
b1 ,
b100 -
b11 .
b0 0
b0 2
b1 5

#240000
0!
0'

#245000
1!
b1 $
1%
1'
b1 *
b1 +
b10 ,
b100 -
b0 .

#246000
b1 0
b1 1
b1 2

#250000
0!
0'

#255000
1!
b10 $
1'
b10 *
b10 +
b100 ,
b100 -
b1 .

#256000
b11 0
b10 1
b10 2

#260000
0!
0'

#265000
1!
b100 $
1'
b100 *
b11 +
b1000 ,
b100 -
b10 .

#266000
b111 0
b100 1
b11 2

#270000
0!
0'

#275000
1!
b1000 $
1'
b1000 *
b0 +
b1 ,
b100 -
b11 .

#276000
b0 #
b0 )
b0 ,
b100 -
b11 .
b1111 0
b1000 1
b100 2
b10 5

#280000
0!
0'

#285000
1!
b0 $
0%
1'
b0 *

#290000
0!
0'

#295000
1!
1'

#296000
0"
0(

#300000
0!
0'

#305000
1!
1'

#310000
0!
0'

#315000
1!
1'

#320000
0!
0'

#325000
1!
1'

#326000
1"
1(

#330000
0!
0'

#335000
1!
1'

#336000
b10 #
b10 )
b10 ,
b100 -
b11 .

#340000
0!
0'

#345000
1!
b10 $
1%
1'
b10 *
b10 +
b10 ,
b100 -
b1 .

#350000
0!
0'

#355000
1!
1'

#356000
b1000 #
b1000 )
b1000 ,
b100 -
b1 .

#360000
0!
0'

#365000
1!
b1000 $
1'
b1000 *
b0 +
b1000 ,
b100 -
b11 .

#370000
0!
0'

#375000
1!
1'

#376000
b0 #
b0 )
b0 ,
b100 -
b11 .

#380000
0!
0'

#385000
1!
b0 $
0%
1'
b0 *

#390000
0!
0'

#395000
1!
1'

#396000
0"
0(

#400000
0!
0'

#405000
1!
1'

#410000
0!
0'

#415000
1!
1'

#420000
0!
0'

#425000
1!
1'

#426000
1"
1(

#430000
0!
0'

#435000
1!
1'

#436000
b100 5

#440000
0!
0'

#445000
1!
1'

#450000
0!
0'

#455000
1!
1'

#460000
0!
0'

#465000
1!
1'

#470000
0!
0'

#475000
1!
1'

#476000
0"
0(

#480000
0!
0'

#485000
1!
1'

#490000
0!
0'

#495000
1!
1'

#500000
0!
0'

#505000
1!
1'

#506000
1"
1(

#510000
0!
0'

#515000
1!
1'

#516000
b1001 #
b1001 )
b1 ,
b100 -
b11 .
b0 3
b0 4
b10 5

#520000
0!
0'

#525000
1!
b1 $
1%
1'
b1 *
b1 +
b1000 ,
b100 -
b0 .

#530000
0!
0'

#535000
1!
b1000 $
1'
b1000 *
b0 +
b1 ,
b100 -
b11 .

#536000
b1 3
b1 4

#540000
0!
0'

#545000
1!
b1 $
1'
b1 *
b1 +
b1000 ,
b100 -
b0 .

#550000
0!
0'

#555000
1!
b1000 $
1'
b1000 *
b0 +
b1 ,
b100 -
b11 .

#556000
b10 3
b10 4

#560000
0!
0'

#565000
1!
b1 $
1'
b1 *
b1 +
b1000 ,
b100 -
b0 .

#570000
0!
0'

#575000
1!
b1000 $
1'
b1000 *
b0 +
b1 ,
b100 -
b11 .

#576000
b11 3
b11 4

#580000
0!
0'

#585000
1!
b1 $
1'
b1 *
b1 +
b1000 ,
b100 -
b0 .

#590000
0!
0'

#595000
1!
b1000 $
1'
b1000 *
b0 +
b1 ,
b100 -
b11 .

#596000
b100 3
b100 4

#600000
0!
0'

#605000
1!
b1 $
1'
b1 *
b1 +
b1000 ,
b100 -
b0 .

#610000
0!
0'

#615000
1!
b1000 $
1'
b1000 *
b0 +
b1 ,
b100 -
b11 .

#616000
b101 3
b101 4

#620000
0!
0'

#625000
1!
b1 $
1'
b1 *
b1 +
b1000 ,
b100 -
b0 .

#630000
0!
0'

#635000
1!
b1000 $
1'
b1000 *
b0 +
b1 ,
b100 -
b11 .

#636000
b110 3
b110 4

#640000
0!
0'

#645000
1!
b1 $
1'
b1 *
b1 +
b1000 ,
b100 -
b0 .

#650000
0!
0'

#655000
1!
b1000 $
1'
b1000 *
b0 +
b1 ,
b100 -
b11 .

#656000
b111 3
b111 4

#660000
0!
0'

#665000
1!
b1 $
1'
b1 *
b1 +
b1000 ,
b100 -
b0 .

#670000
0!
0'

#675000
1!
b1000 $
1'
b1000 *
b0 +
b1 ,
b100 -
b11 .

#676000
b1000 3
b1000 4
